README.rst
setup.cfg
setup.py
charlesbot_pagerduty_escalations/__init__.py
charlesbot_pagerduty_escalations/http.py
charlesbot_pagerduty_escalations/pagerdutyescalations.py
charlesbot_pagerduty_escalations.egg-info/PKG-INFO
charlesbot_pagerduty_escalations.egg-info/SOURCES.txt
charlesbot_pagerduty_escalations.egg-info/dependency_links.txt
charlesbot_pagerduty_escalations.egg-info/not-zip-safe
charlesbot_pagerduty_escalations.egg-info/requires.txt
charlesbot_pagerduty_escalations.egg-info/top_level.txt