Metadata-Version: 1.1
Name: charlesbot-pagerduty-escalations
Version: 0.1.0
Summary: Plugin to create an incident in Pagerduty and assign it to a specific team
Home-page: https://github.com/freshbooks/charlesbot-pagerduty-escalations
Author: FreshBooks
Author-email: morpheus@freshbooks.com
License: MIT
Keywords: slack robot chatops charlesbot charlesbot-pagerduty-escalations
Platform: UNKNOWN
Classifier: Development Status :: 3 - Alpha
Classifier: Intended Audience :: Developers
Classifier: License :: OSI Approved :: MIT License
Classifier: Programming Language :: Python :: 3.4
